{"expireTime":9007200881476559000,"key":"198eadc9c6b6884f26eecb3ee132949e","val":{"name":"IMAGE_PROCESSING","inputPaths":["/home/codin_champ/Desktop/College Documents/College Assignments/codin-champ.github.io/content/featured/Directory-Manager/employee-directory-software.png"],"outputDir":"/home/codin_champ/Desktop/College Documents/College Assignments/codin-champ.github.io/public/static/5b98855afe776e7e71204c42ea0e5f7b","args":{"isLazy":false,"operations":[{"outputPath":"847ef/employee-directory-software.png","args":{"width":175,"cropFocus":17,"toFormat":"png","quality":90,"fit":"cover","background":"rgba(0,0,0,1)"}},{"outputPath":"91cba/employee-directory-software.png","args":{"width":350,"cropFocus":17,"toFormat":"png","quality":90,"fit":"cover","background":"rgba(0,0,0,1)"}},{"outputPath":"60290/employee-directory-software.png","args":{"width":700,"cropFocus":17,"toFormat":"png","quality":90,"fit":"cover","background":"rgba(0,0,0,1)"}},{"outputPath":"f5f50/employee-directory-software.png","args":{"width":1050,"cropFocus":17,"toFormat":"png","quality":90,"fit":"cover","background":"rgba(0,0,0,1)"}},{"outputPath":"73f08/employee-directory-software.png","args":{"width":1200,"cropFocus":17,"toFormat":"png","quality":90,"fit":"cover","background":"rgba(0,0,0,1)"}}],"pluginOptions":{"base64Width":20,"forceBase64Format":"","useMozJpeg":false,"stripMetadata":true,"lazyImageGeneration":true,"defaultQuality":50,"failOnError":true,"plugins":[]}}}}